st_aggrid/AgGrid.py
st_aggrid/AgGridReturn.py
st_aggrid/__init__.py
st_aggrid/aggrid_utils.py
st_aggrid/collectors/__init__.py
st_aggrid/collectors/base.py
st_aggrid/collectors/custom.py
st_aggrid/collectors/factory.py
st_aggrid/collectors/legacy.py
st_aggrid/collectors/minimal.py
st_aggrid/frontend/build/asset-manifest.json
st_aggrid/frontend/build/bootstrap.min.css
st_aggrid/frontend/build/bootstrap.min.css.map
st_aggrid/frontend/build/index.html
st_aggrid/frontend/build/static/css/main.06956719.css
st_aggrid/frontend/build/static/css/main.06956719.css.map
st_aggrid/frontend/build/static/js/main.f4bb7ae6.js
st_aggrid/frontend/build/static/js/main.f4bb7ae6.js.LICENSE.txt
st_aggrid/frontend/build/static/js/main.f4bb7ae6.js.map
st_aggrid/frontend/build/static/media/source-sans-pro-cyrillic-400-normal.153bee8d873292f9df39.woff2
st_aggrid/frontend/build/static/media/source-sans-pro-cyrillic-400-normal.a00a7030792ec450d68c.woff
st_aggrid/frontend/build/static/media/source-sans-pro-cyrillic-ext-400-normal.3fe9e8e4c00e9124b9c7.woff
st_aggrid/frontend/build/static/media/source-sans-pro-cyrillic-ext-400-normal.de95c5209ef26bf69ccf.woff2
st_aggrid/frontend/build/static/media/source-sans-pro-greek-400-normal.3c06b5e22c42ade5562f.woff
st_aggrid/frontend/build/static/media/source-sans-pro-greek-400-normal.9c7d72dcc7a044db07b1.woff2
st_aggrid/frontend/build/static/media/source-sans-pro-greek-ext-400-normal.1b1cb10170f2616853f0.woff2
st_aggrid/frontend/build/static/media/source-sans-pro-greek-ext-400-normal.7a64c855edb8d403283b.woff
st_aggrid/frontend/build/static/media/source-sans-pro-latin-400-normal.1402accbefdec6a25762.woff2
st_aggrid/frontend/build/static/media/source-sans-pro-latin-400-normal.7a5ba508b998fd7044ed.woff
st_aggrid/frontend/build/static/media/source-sans-pro-latin-ext-400-normal.185cedfb4e64a9a8801a.woff
st_aggrid/frontend/build/static/media/source-sans-pro-latin-ext-400-normal.23e9c5217d09910f51ad.woff2
streamlit_aggrid-1.2.0.post2.dist-info/LICENSE
streamlit_aggrid-1.2.0.post2.dist-info/METADATA
streamlit_aggrid-1.2.0.post2.dist-info/WHEEL
streamlit_aggrid-1.2.0.post2.dist-info/RECORD
