Metadata-Version: 2.3
Name: streamlit-aggrid
Version: 1.2.0.post2
Summary: Streamlit component implementation of ag-grid
License: MIT
Keywords: streamlit,ag-grid,component
Author: Pablo Fonseca
Author-email: pablo.fonseca+pip@gmail.com
Requires-Python: >=3.10
Classifier: License :: OSI Approved :: MIT License
Classifier: Operating System :: OS Independent
Classifier: Programming Language :: Python :: 3
Classifier: Programming Language :: Python :: 3.10
Classifier: Programming Language :: Python :: 3.11
Classifier: Programming Language :: Python :: 3.12
Classifier: Programming Language :: Python :: 3.13
Requires-Dist: pandas (>=1.4.0)
Requires-Dist: python-decouple
Requires-Dist: streamlit (>=1.2)
Project-URL: Homepage, https://github.com/PablocFonseca/streamlit-aggrid
